pydomaintextfeature
